ladybug/WMM.COF
ladybug/__init__.py
ladybug/__main__.py
ladybug/_datacollectionbase.py
ladybug/analysisperiod.py
ladybug/climatezone.py
ladybug/color.py
ladybug/commandutil.py
ladybug/compass.py
ladybug/config.json
ladybug/config.py
ladybug/datacollection.py
ladybug/datacollectionimmutable.py
ladybug/datautil.py
ladybug/ddy.py
ladybug/designday.py
ladybug/dt.py
ladybug/epw.py
ladybug/futil.py
ladybug/graphic.py
ladybug/header.py
ladybug/hourlyplot.py
ladybug/legend.py
ladybug/location.py
ladybug/logutil.py
ladybug/monthlychart.py
ladybug/north.py
ladybug/psychchart.py
ladybug/psychrometrics.py
ladybug/rootfinding.py
ladybug/skymodel.py
ladybug/solarenvelope.py
ladybug/sql.py
ladybug/stat.py
ladybug/sunpath.py
ladybug/viewsphere.py
ladybug/wea.py
ladybug/windprofile.py
ladybug/windrose.py
ladybug/cli/__init__.py
ladybug/cli/_helper.py
ladybug/cli/setconfig.py
ladybug/cli/translate.py
ladybug/datatype/__init__.py
ladybug/datatype/angle.py
ladybug/datatype/area.py
ladybug/datatype/base.py
ladybug/datatype/conductance.py
ladybug/datatype/conductivity.py
ladybug/datatype/current.py
ladybug/datatype/density.py
ladybug/datatype/distance.py
ladybug/datatype/energy.py
ladybug/datatype/energyflux.py
ladybug/datatype/energyintensity.py
ladybug/datatype/fraction.py
ladybug/datatype/generic.py
ladybug/datatype/illuminance.py
ladybug/datatype/luminance.py
ladybug/datatype/mass.py
ladybug/datatype/massflowrate.py
ladybug/datatype/power.py
ladybug/datatype/pressure.py
ladybug/datatype/resistance.py
ladybug/datatype/resistivity.py
ladybug/datatype/rvalue.py
ladybug/datatype/specificenergy.py
ladybug/datatype/specificheatcapacity.py
ladybug/datatype/speed.py
ladybug/datatype/temperature.py
ladybug/datatype/temperaturedelta.py
ladybug/datatype/temperaturetime.py
ladybug/datatype/thermalcondition.py
ladybug/datatype/time.py
ladybug/datatype/uvalue.py
ladybug/datatype/voltage.py
ladybug/datatype/volume.py
ladybug/datatype/volumeflowrate.py
ladybug/datatype/volumeflowrateintensity.py
ladybug_core-0.44.32.dist-info/licenses/LICENSE
ladybug_core-0.44.32.dist-info/METADATA
ladybug_core-0.44.32.dist-info/WHEEL
ladybug_core-0.44.32.dist-info/entry_points.txt
ladybug_core-0.44.32.dist-info/top_level.txt
ladybug_core-0.44.32.dist-info/RECORD
